Workbook

Sheet Dataset_Documentos
A1: documento_id | B1: tipo_documento | C1: titulo_documento | D1: fecha_documento | E1: entidad_origen | F1: area_responsable | G1: categoria | H1: estado | I1: nivel_confidencialidad | J1: prioridad | K1: texto_documento | L1: resumen_documento | M1: palabras_clave | N1: pregunta_ejemplo | O1: respuesta_esperada | P1: fuente_archivo | Q1: observaciones
A2: DOC-0001 | B2: Acta | C2: Acta sobre arquitectura tecnológica - Luz del Sur | D2: 45779 | E2: Luz del Sur | F2: QA | G2: Técnico | H2: Archivado | I2: Público | J2: Alta | K2: El presente documento corresponde a un acta emitido por Luz del Sur, relacionado con arquitectura tecnológica, seguridad y integración de sistemas. El área responsable es QA. Se solicita revisar los antecedentes, validar la información registrada, verificar el estado archivado y confirmar las acciones necesarias. El documento contiene información para la gestión documental, consulta posterior, trazabilidad, análisis semántico y soporte a decisiones. Como parte del proceso, se debe identificar responsables, fechas, riesgos, obligaciones y posibles acciones de seguimiento. Este texto está preparado para ser usado por un agente de IA que permita consultar documentos, recuperar información relevante y responder preguntas del usuario con base en el contenido registrado. | L2: Acta de Luz del Sur asociado a arquitectura tecnológica y gestionado por QA. | M2: Técnico, Acta, arquitectura tecnológica, seguridad, integración de sistemas | N2: ¿Qué indica el documento DOC-0001 sobre arquitectura tecnológica? | O2: El documento DOC-0001 indica que se debe revisar arquitectura tecnológica, validar antecedentes y coordinar acciones con el área QA. | P2: DOC-0001_Acta.pdf | Q2: Registro sintético para entrenamiento inicial del agente documental.
A3: DOC-0002 | B3: Informe Técnico | C3: Informe Técnico sobre alcance comercial - Caja Cusco | D3: 46012 | E3: Caja Cusco | F3: TI | G3: Comercial | H3: Pendiente | I3: Interno | J3: Media | K3: El presente documento corresponde a un informe técnico emitido por Caja Cusco, relacionado con alcance comercial, renovación y servicio contratado. El área responsable es TI. Se solicita revisar los antecedentes, validar la información registrada, verificar el estado pendiente y confirmar las acciones necesarias. El documento contiene información para la gestión documental, consulta posterior, trazabilidad, análisis semántico y soporte a decisiones. Como parte del proceso, se debe identificar responsables, fechas, riesgos, obligaciones y posibles acciones de seguimiento. Este texto está preparado para ser usado por un agente de IA que permita consultar documentos, recuperar información relevante y responder preguntas del usuario con base en el contenido registrado. | L3: Informe Técnico de Caja Cusco asociado a alcance comercial y gestionado por TI. | M3: Comercial, Informe Técnico, alcance comercial, renovación, servicio contratado | N3: ¿Qué indica el documento DOC-0002 sobre alcance comercial? | O3: El documento DOC-0002 indica que se debe revisar alcance comercial, validar antecedentes y coordinar acciones con el área TI. | P3: DOC-0002_Informe_Técnico.pdf | Q3: Registro sintético para entrenamiento inicial del agente documental.
A4: DOC-0003 | B4: Memorando | C4: Memorando sobre archivo - APN | D4: 45931 | E4: APN | F4: Soporte | G4: Administrativo | H4: Observado | I4: Interno | J4: Media | K4: El presente documento corresponde a un memorando emitido por APN, relacionado con archivo, registro documentario y aprobación. El área responsable es Soporte. Se solicita revisar los antecedentes, validar la información registrada, verificar el estado observado y confirmar las acciones necesarias. El documento contiene información para la gestión documental, consulta posterior, trazabilidad, análisis semántico y soporte a decisiones. Como parte del proceso, se debe identificar responsables, fechas, riesgos, obligaciones y posibles acciones de seguimiento. Este texto está preparado para ser usado por un agente de IA que permita consultar documentos, recuperar información relevante y responder preguntas del usuario con base en el contenido registrado. | L4: Memorando de APN asociado a archivo y gestionado por Soporte. | M4: Administrativo, Memorando, archivo, registro documentario, aprobación | N4: ¿Qué indica el documento DOC-0003 sobre archivo? | O4: El documento DOC-0003 indica que se debe revisar archivo, validar antecedentes y coordinar acciones con el área Soporte. | P4: DOC-0003_Memorando.pdf | Q4: Registro sintético para entrenamiento inicial del agente documental.
A5: DOC-0004 | B5: Carta | C5: Carta sobre monto - Grupo Gloria | D5: 45956 | E5: Grupo Gloria | F5: Gestión Documental | G5: Financiero | H5: Vigente | I5: Interno | J5: Crítica | K5: El presente documento corresponde a un carta emitido por Grupo Gloria, relacionado con monto, validación contable y orden de compra. El área responsable es Gestión Documental. Se solicita revisar los antecedentes, validar la información registrada, verificar el estado vigente y confirmar las acciones necesarias. El documento contiene información para la gestión documental, consulta posterior, trazabilidad, análisis semántico y soporte a decisiones. Como parte del proceso, se debe identificar responsables, fechas, riesgos, obligaciones y posibles acciones de seguimiento. Este texto está preparado para ser usado por un agente de IA que permita consultar documentos, recuperar información relevante y responder preguntas del usuario con base en el contenido registrado. | L5: Carta de Grupo Gloria asociado a monto y gestionado por Gestión Documental. | M5: Financiero, Carta, monto, validación contable, orden de compra | N5: ¿Qué indica el documento DOC-0004 sobre monto? | O5: El documento DOC-0004 indica que se debe revisar monto, validar antecedentes y coordinar acciones con el área Gestión Documental. | P5: DOC-0004_Carta.pdf | Q5: Registro sintético para entrenamiento inicial del agente documental.
A6: DOC-0005 | B6: Solicitud | C6: Solicitud sobre renovación - Osinergmin | D6: 45933 | E6: Osinergmin | F6: Gestión Documental | G6: Comercial | H6: Archivado | I6: Público | J6: Crítica | K6: El presente documento corresponde a un solicitud emitido por Osinergmin, relacionado con renovación, servicio contratado y condiciones de pago. El área responsable es Gestión Documental. Se solicita revisar los antecedentes, validar la información registrada, verificar el estado archivado y confirmar las acciones necesarias. El documento contiene información para la gestión documental, consulta posterior, trazabilidad, análisis semántico y soporte a decisiones. Como parte del proceso, se debe identificar responsables, fechas, riesgos, obligaciones y posibles acciones de seguimiento. Este texto está preparado para ser usado por un agente de IA que permita consultar documentos, recuperar información relevante y responder preguntas del usuario con base en el contenido registrado. | L6: Solicitud de Osinergmin asociado a renovación y gestionado por Gestión Documental. | M6: Comercial, Solicitud, renovación, servicio contratado, condiciones de pago | N6: ¿Qué indica el documento DOC-0005 sobre renovación? | O6: El documento DOC-0005 indica que se debe revisar renovación, validar antecedentes y coordinar acciones con el área Gestión Documental. | P6: DOC-0005_Solicitud.pdf | Q6: Registro sintético para entrenamiento inicial del agente documental.
A7: DOC-0006 | B7: Resolución | C7: Resolución sobre cláusulas de servicio - COES | D7: 45964 | E7: COES | F7: QA | G7: Legal | H7: Pendiente | I7: Público | J7: Alta | K7: El presente documento corresponde a un resolución emitido por COES, relacionado con cláusulas de servicio, penalidades y vigencia contractual. El área responsable es QA. Se solicita revisar los antecedentes, validar la información registrada, verificar el estado pendiente y confirmar las acciones necesarias. El documento contiene información para la gestión documental, consulta posterior, trazabilidad, análisis semántico y soporte a decisiones. Como parte del proceso, se debe identificar responsables, fechas, riesgos, obligaciones y posibles acciones de seguimiento. Este texto está preparado para ser usado por un agente de IA que permita consultar documentos, recuperar información relevante y responder preguntas del usuario con base en el contenido registrado. | L7: Resolución de COES asociado a cláusulas de servicio y gestionado por QA. | M7: Legal, Resolución, cláusulas de servicio, penalidades, vigencia contractual | N7: ¿Qué indica el documento DOC-0006 sobre cláusulas de servicio? | O7: El documento DOC-0006 indica que se debe revisar cláusulas de servicio, validar antecedentes y coordinar acciones con el área QA. | P7: DOC-0006_Resolución.pdf | Q7: Registro sintético para entrenamiento inicial del agente documental.
A8: DOC-0007 | B8: Memorando | C8: Memorando sobre cláusulas de servicio - Servir | D8: 46039 | E8: Servir | F8: Soporte | G8: Legal | H8: Observado | I8: Interno | J8: Baja | K8: El presente documento corresponde a un memorando emitido por Servir, relacionado con cláusulas de servicio, vigencia contractual y penalidades. El área responsable es Soporte. Se solicita revisar los antecedentes, validar la información registrada, verificar el estado observado y confirmar las acciones necesarias. El documento contiene información para la gestión documental, consulta posterior, trazabilidad, análisis semántico y soporte a decisiones. Como parte del proceso, se debe identificar responsables, fechas, riesgos, obligaciones y posibles acciones de seguimiento. Este texto está preparado para ser usado por un agente de IA que permita consultar documentos, recuperar información relevante y responder preguntas del usuario con base en el contenido registrado. | L8: Memorando de Servir asociado a cláusulas de servicio y gestionado por Soporte. | M8: Legal, Memorando, cláusulas de servicio, vigencia contractual, penalidades | N8: ¿Qué indica el documento DOC-0007 sobre cláusulas de servicio? | O8: El documento DOC-0007 indica que se debe revisar cláusulas de servicio, validar antecedentes y coordinar acciones con el área Soporte. | P8: DOC-0007_Memorando.pdf | Q8: Registro sintético para entrenamiento inicial del agente documental.
A9: DOC-0008 | B9: Acta | C9: Acta sobre archivo - APN | D9: 45831 | E9: APN | F9: Administración | G9: Administrativo | H9: Observado | I9: Interno | J9: Crítica | K9: El presente documento corresponde a un acta emitido por APN, relacionado con archivo, derivación interna y seguimiento. El área responsable es Administración. Se solicita revisar los antecedentes, validar la información registrada, verificar el estado observado y confirmar las acciones necesarias. El documento contiene información para la gestión documental, consulta posterior, trazabilidad, análisis semántico y soporte a decisiones. Como parte del proceso, se debe identificar responsables, fechas, riesgos, obligaciones y posibles acciones de seguimiento. Este texto está preparado para ser usado por un agente de IA que permita consultar documentos, recuperar información relevante y responder preguntas del usuario con base en el contenido registrado. | L9: Acta de APN asociado a archivo y gestionado por Administración. | M9: Administrativo, Acta, archivo, derivación interna, seguimiento | N9: ¿Qué indica el documento DOC-0008 sobre archivo? | O9: El documento DOC-0008 indica que se debe revisar archivo, validar antecedentes y coordinar acciones con el área Administración. | P9: DOC-0008_Acta.pdf | Q9: Registro sintético para entrenamiento inicial del agente documental.
A10: DOC-0009 | B10: Expediente | C10: Expediente sobre integración de sistemas - OEFA | D10: 45822 | E10: OEFA | F10: QA | G10: Técnico | H10: En revisión | I10: Interno | J10: Alta | K10: El presente documento corresponde a un expediente emitido por OEFA, relacionado con integración de sistemas, disponibilidad y arquitectura tecnológica. El área responsable es QA. Se solicita revisar los antecedentes, validar la información registrada, verificar el estado en revisión y confirmar las acciones necesarias. El documento contiene información para la gestión documental, consulta posterior, trazabilidad, análisis semántico y soporte a decisiones. Como parte del proceso, se debe identificar responsables, fechas, riesgos, obligaciones y posibles acciones de seguimiento. Este texto está preparado para ser usado por un agente de IA que permita consultar documentos, recuperar información relevante y responder preguntas del usuario con base en el contenido registrado. | L10: Expediente de OEFA asociado a integración de sistemas y gestionado por QA. | M10: Técnico, Expediente, integración de sistemas, disponibilidad, arquitectura tecnológica | N10: ¿Qué indica el documento DOC-0009 sobre integración de sistemas? | O10: El documento DOC-0009 indica que se debe revisar integración de sistemas, validar antecedentes y coordinar acciones con el área QA. | P10: DOC-0009_Expediente.pdf | Q10: Registro sintético para entrenamiento inicial del agente documental.
A11: DOC-0010 | B11: Acta | C11: Acta sobre alcance comercial - Sunass | D11: 45827 | E11: Sunass | F11: TI | G11: Comercial | H11: Observado | I11: Interno | J11: Media | K11: El presente documento corresponde a un acta emitido por Sunass, relacionado con alcance comercial, servicio contratado y condiciones de pago. El área responsable es TI. Se solicita revisar los antecedentes, validar la información registrada, verificar el estado observado y confirmar las acciones necesarias. El documento contiene información para la gestión documental, consulta posterior, trazabilidad, análisis semántico y soporte a decisiones. Como parte del proceso, se debe identificar responsables, fechas, riesgos, obligaciones y posibles acciones de seguimiento. Este texto está preparado para ser usado por un agente de IA que permita consultar documentos, recuperar información relevante y responder preguntas del usuario con base en el contenido registrado. | L11: Acta de Sunass asociado a alcance comercial y gestionado por TI. | M11: Comercial, Acta, alcance comercial, servicio contratado, condiciones de pago | N11: ¿Qué indica el documento DOC-0010 sobre alcance comercial? | O11: El documento DOC-0010 indica que se debe revisar alcance comercial, validar antecedentes y coordinar acciones con el área TI. | P11: DOC-0010_Acta.pdf | Q11: Registro sintético para entrenamiento inicial del agente documental.
A12: DOC-0011 | B12: Acta | C12: Acta sobre facturación - BTG | D12: 45959 | E12: BTG | F12: Soporte | G12: Financiero | H12: Pendiente | I12: Interno | J12: Media | K12: El presente documento corresponde a un acta emitido por BTG, relacionado con facturación, orden de compra y monto. El área responsable es Soporte. Se solicita revisar los antecedentes, validar la información registrada, verificar el estado pendiente y confirmar las acciones necesarias. El documento contiene información para la gestión documental, consulta posterior, trazabilidad, análisis semántico y soporte a decisiones. Como parte del proceso, se debe identificar responsables, fechas, riesgos, obligaciones y posibles acciones de seguimiento. Este texto está preparado para ser usado por un agente de IA que permita consultar documentos, recuperar información relevante y responder preguntas del usuario con base en el contenido registrado. | L12: Acta de BTG asociado a facturación y gestionado por Soporte. | M12: Financiero, Acta, facturación, orden de compra, monto | N12: ¿Qué indica el documento DOC-0011 sobre facturación? | O12: El documento DOC-0011 indica que se debe revisar facturación, validar antecedentes y coordinar acciones con el área Soporte. | P12: DOC-0011_Acta.pdf | Q12: Registro sintético para entrenamiento inicial del agente documental.
A13: DOC-0012 | B13: Resolución | C13: Resolución sobre seguimiento - Luz del Sur | D13: 46006 | E13: Luz del Sur | F13: Administración | G13: Administrativo | H13: Pendiente | I13: Interno | J13: Alta | K13: El presente documento corresponde a un resolución emitido por Luz del Sur, relacionado con seguimiento, registro documentario y aprobación. El área responsable es Administración. Se solicita revisar los antecedentes, validar la información registrada, verificar el estado pendiente y confirmar las acciones necesarias. El documento contiene información para la gestión documental, consulta posterior, trazabilidad, análisis semántico y soporte a decisiones. Como parte del proceso, se debe identificar responsables, fechas, riesgos, obligaciones y posibles acciones de seguimiento. Este texto está preparado para ser usado por un agente de IA que permita consultar documentos, recuperar información relevante y responder preguntas del usuario con base en el contenido registrado. | L13: Resolución de Luz del Sur asociado a seguimiento y gestionado por Administración. | M13: Administrativo, Resolución, seguimiento, registro documentario, aprobación | N13: ¿Qué indica el documento DOC-0012 sobre seguimiento? | O13: El documento DOC-0012 indica que se debe revisar seguimiento, validar antecedentes y coordinar acciones con el área Administración. | P13: DOC-0012_Resolución.pdf | Q13: Registro sintético para entrenamiento inicial del agente documental.
... A201: DOC-0200 | B201: Oficio | C201: Oficio sobre validación contable - Servir | D201: 46156 | E201: Servir | F201: Operaciones | G201: Financiero | H201: Pendiente | I201: Público | J201: Media | K201: El presente documento corresponde a un oficio emitido por Servir, relacionado con validación contable, monto y facturación. El área responsable es Operaciones. Se solicita revisar los antecedentes, validar la información registrada, verificar el estado pendiente y confirmar las acciones necesarias. El documento contiene información para la gestión documental, consulta posterior, trazabilidad, análisis semántico y soporte a decisiones. Como parte del proceso, se debe identificar responsables, fechas, riesgos, obligaciones y posibles acciones de seguimiento. Este texto está preparado para ser usado por un agente de IA que permita consultar documentos, recuperar información relevante y responder preguntas del usuario con base en el contenido registrado. | L201: Oficio de Servir asociado a validación contable y gestionado por Operaciones. | M201: Financiero, Oficio, validación contable, monto, facturación | N201: ¿Qué indica el documento DOC-0200 sobre validación contable? | O201: El documento DOC-0200 indica que se debe revisar validación contable, validar antecedentes y coordinar acciones con el área Operaciones. | P201: DOC-0200_Oficio.pdf | Q201: Registro sintético para entrenamiento inicial del agente documental.
A202: DOC-0201 | B202: Contrato | C202: CONTRATO-SERVICIOS DESARROLLO TI - BTG y TOP 2026 | D202: 18/05/2026 | G202: Documental | H202: Pendiente | I202: Interno | J202: Baja | K202: CONTRATO DE PRESTACIONES DE SERVICIOS Conste por el presente documento el Contrato de Prestación Servicios según Decreto Legislativo N° 25632, de una parte, TOPSTRATEGIC S.A.C, con RUC N° 20516818353, debidamente representada por su Gerente General, Señora Maria Karelia Yepez Azparren, identificada con DNI Nº 47874682 con poderes inscritos en el Registro de Personas Jurídicas de Lima, a quien en adelante se le denominará “EL CLIENTE”, y de la otra parte, Señora Jandyra Pilar Villanueva Panduro, con DNI 431447667 en representación de la empresa BTG S.A.C. con RUC 20511469997, con domicilio en Jr. Huarmey 1224 – Urb. Covida- Los Olivos Lima, a quien en adelante se le denominará “EL PROVEEDOR”, en los términos y condiciones siguientes: CLAUSULA PRIMERA - ANTECEDENTES: El CLIENTE, requiere contratar los servicios de una empresa privada que realice labores de desarrollo e innovación tecnológica, para la actualización de sus Soluciones Tecnológicas, lo cual constituye una obligación de hacer de conformidad al artículo 1148 del Código Civil, el cual debidamente suscrito por las partes forma parte integrante del presente contrato. CLAUSULA SEGUNDA - OBJETO DEL CONTRATO: El PROVEEDOR, sin mantener vínculo alguno de subordinación ni dependencia con el CLIENTE, en su condición de empresa especializada en el análisis y desarrollo de software de aplicaciones, quien prestará sus servicios bajo un régimen No Fiscalizable, se obliga a prestarle sus servicios profesionales en el proyecto de implementación y/o upgrade de nuevas tecnologías informáticas, para la Solución de Liquidación Bruta a Tiempo Real – LBTR - 1RA Fase. Dichas mejoras se detallan en el ANEXO 1 – que forma parte del presente contrato. CLAUSULA TERCERA - RETRIBUCIONES Y FORMA DE PAGO: El CLIENTE pagará al PROVEEDOR, como contraprestación por la totalidad de sus servicios según avances, el monto es de USD. 41,768.06 - (Cuarenta y Un Mil Setecientos Sesenta y Ocho con 06/100 dólares americanos) incluido el Impuesto General a las Ventas, previa conformidad del trabajo realizado en términos de resultados (calidad, puntualidad y resultados planificados), en el plazo de duración del proyecto, la misma que le será abonada conforme al avance de los servicios prestados. CLAUSULA CUARTA – PLAZO DEL CONTRATO El plazo del presente contrato será por el periodo de dos (2) meses calendarios, contado a partir de la fecha de firma del contrato. En caso de no terminarse la prestación del servicio en el plazo estipulado, las partes convienen que tal plazo podrá renovarse de común acuerdo para lo cual deberán necesariamente suscribir por escrito tal renovación. CLAUSULA QUINTA El PROVEEDOR prestará sus servicios en los horarios que estime conveniente, coordinando los tiempos de disponibilidad de equipos tecnológicos y del equipo de los usuarios participantes en el proyecto para efectos de pruebas y de ajuste de requerimientos funcionales, en el ámbito de los alcances y objetivos del proyecto. CLAUSULA SEXTA El servicio que prestará el PROVEEDOR al CLIENTE, serán de carácter personalísimo, pero puede valerse, bajo su propia dirección y responsabilidad de auxiliares y sustitutos para prestar tales servicios. El PROVEEDOR deberá respetar el CONVENIO DE CONFIDENCIALIDAD y PROTECCION DE DATOS PERSONALES, reconociendo que su incumplimiento constituye falta grave de orden laboral, dándose a lugar la imposición de sanciones que irán desde la simple amonestación hasta el despido, sin perjuicio de las acciones civiles o penales a que haya a lugar. CLAUSULA SEPTIMA – RESOLUCION DE CONTRATO EL CLIENTE podrá resolver el contrato en caso de incumplimiento de alguna de las responsabilidades u obligaciones establecidas en el momento de la contratación por parte de EL PROVEEDOR o por Culminación exitosa del Proyecto sin previo aviso por parte del CLIENTE. El PROVEEDOR, si deseara culminar anticipadamente el contrato por voluntad propia, se obliga a avisar de esta voluntad, mediante notificación escrita, con una anticipación no menor de 30 días calendarios. CLAUSULA OCTAVA - IMPUESTOS: EL CLIENTE detraerá un porcentaje del monto total de la operación por la venta de ciertos bienes y/o servicios conforme a Resolución Superintendencia 071-2018/SUNAT, estos son depositados en una cuenta especial en el Banco de la Nación a nombre del proveedor o prestador del servicio, estos fondos serán utilizados para el pago de deudas tributarias administradas y/o recaudadas por la SUNAT. CLAUSULA NOVENA – OBLIGACIONES DE LAS PARTES El PROVEEDOR se obliga a prestar sus servicios a satisfacción del CLIENTE, con profesionalismo asumiendo la responsabilidad sobre los trabajos que ejecutará. Asimismo, se compromete a asistir a las oficinas del CLIENTE en las oportunidades que sea necesario, teniéndose en cuenta que los servicios que prestará serán predominantemente intelectuales. Por su parte el CLIENTE se obliga a proporcionar al PROVEEDOR las facilidades necesarias para la prestación de sus servicios, así como el pago de su retribución en la forma que se ha convenido y que se indican en el ANEXO 1, que forma parte del presente contrato, siempre y cuando el PROVEEDOR haya terminado las actividades encargadas y sus resultados sean satisfactorios para el CLIENTE. CLAUSULA DECIMA – PENALIDAD El PROVEEDOR, deberá cumplir con su prestación de servicios a cabalidad hasta la finalización del presente contrato. En caso el PROVEEDOR desee finalizar el contrato antes de su vencimiento deberá dirigir una carta al CLIENTE notificando su deseo de no continuar su relación contractual, con una anticipación de 30 días hábiles, de lo contrario se le aplicara una penalidad y se le descontará el 20% del pago por su contraprestación. CLAUSULA DECIMA PRIMERA - JURISDICCION: Ambas partes señalan como sus domicilios los que figuran en la introducción de contrato, obligándose en caso de variarlo, a hacerlo conocer a la otra parte por escrito en el plazo máximo de 07 (siete) días naturales, de lo contrario se tendrán por bien hecha cualquier comunicación ó notificación que una parte remita a la otra, o la que haga la autoridad competente: Asimismo, ambas partes se someten a los Jueces del Distrito Judicial de Lima, para cualquier asunto que se derive del presente contrato. Enterados de su contenido y en señal de su conformidad, las partes suscriben el presente contrato en un ejemplar a los nueve días del mes de mayo del 2026. EL CLIENTE EL PROVEEDOR BTG SAC Jandyra Villanueva Panduro Notificaciones: jvillanueva@btg.com ANEXO 1 ALCANCES DE LAS MEJORAS AL SISTEMA DE LIQUIDACION BRUTA A TIEMPO REAL - LBTR 1. Implementar la versión LBTR 2.0 con las mejoras tecnológicas basadas en Micro Servicios. 2. Implementar un sistema que permita consumir los servicios ofrecidos por el BCRP como parte del proyecto de modernización del sistema LBTR. Dichos servicios permitirán contar con un canal para la gestión de cuentas corrientes que el CLIENTE mantiene en el BCRP. 3. Eliminar la digitación de datos recurrentes en las instrucciones de transferencia que actualmente son ingresadas por el asistente de backoffice al momento de cada operación (cuenta corriente matriz, cuenta interbancaria, etc.). 4. Implementar los mismos niveles de autorización disponibles en el actual cliente LBTR en el nuevo sistema LBTR. 5. Facilitar el ingreso de instrucciones de transferencias en el nuevo sistema LBTR, mediante el enlace de operaciones ingresadas en los sistemas Operativo del negocio cuyo registro o cancelación este asociado a la transferencia de fondos a través de las cuentas matrices del CLIENTE en el BCRP. Asimismo, los desembolsos de parte de EL CLIENTE para EL PROVEEDOR se realizarán según avances y de acuerdo al siguiente calendario: Entregable Fecha Presentación Importe en USD Condición de Pago Revisión, y Análisis 18/05/2026 USD 18,888.06 Presentación y del Sistema LBTR Aprobación de Informe Implementación de 30/05/2026 USD 11,440.00 Presentación y Micro Servicios Fase 1 Aprobación del Código fuente actualizado Implementación de 15/06/2025 USD 11,440.00 Presentación y Micro Servicios Fase 2 Aprobación del Código fuente actualizado Estos importes incluyen IGV Enterados de su contenido y en señal de su conformidad, las partes suscriben el presente contrato en un ejemplar a los nueve días del mes de mayo del 2026 EL PROVEEDOR EL CLIENTE BTG SAC Jandyra Villanueva Panduro Notificaciones: jvillanueva@btg.com | L202: CONTRATO DE PRESTACIONES DE SERVICIOS Conste por el presente documento el Contrato de Prestación Servicios según Decreto Legislativo N° 25632, de una parte, TOPSTRATEGIC S.A.C, con RUC N° 20516818353, debidamente representada por su Gerente General, ... | N202: ¿Qué indica el documento DOC-0201? | O202: CONTRATO DE PRESTACIONES DE SERVICIOS Conste por el presente documento el Contrato de Prestación Servicios según Decreto Legislativo N° 25632, de una parte, TOPSTRATEGIC S.A.C, con RUC N° 20516818353, debidamente representada por su Gerente General, Señora Maria Karelia Yepez Azparren, identificada con DNI Nº 47874682 con poderes inscritos en el Re... | P202: CONTRATO-SERVICIOS DESARROLLO TI - BTG y TOP 2026.pdf | Q202: Tipificado automáticamente con método: Regla fuerte contractual. Confianza: 95%.

Sheet Catalogos
A1: tipo_documento | B1: categoria | C1: estado | D1: nivel_confidencialidad | E1: prioridad | F1: area_responsable
A2: Contrato | B2: Legal | C2: Vigente | D2: Público | E2: Baja | F2: Mesa de Partes
A3: Oficio | B3: Comercial | C3: Archivado | D3: Interno | E3: Media | F3: Legal
A4: Informe Técnico | B4: Técnico | C4: Pendiente | D4: Confidencial | E4: Alta | F4: TI
A5: Carta | B5: Administrativo | C5: Observado | E5: Crítica | F5: Operaciones
A6: Acta | B6: Operaciones | C6: En revisión | F6: Comercial
A7: Resolución | B7: Financiero | F7: Soporte
A8: Solicitud | B8: Soporte | F8: Gestión Documental
A9: Memorando | B9: Gestión Documental | F9: Administración
A10: Expediente | F10: QA
A11: Reclamo

Sheet Diccionario_Campos
A1: Campo | B1: Descripción | C1: Ejemplo
A2: documento_id | B2: Código único del documento. | C2: DOC-0001
A3: tipo_documento | B3: Tipo documental para clasificar y filtrar. | C3: Contrato
A4: titulo_documento | B4: Título corto del documento. | C4: Contrato sobre SLA - Cliente
A5: fecha_documento | B5: Fecha de emisión o registro. | C5: 2025-10-15
A6: entidad_origen | B6: Cliente, institución o área que origina el documento. | C6: Luz del Sur
A7: area_responsable | B7: Área que debe atender o consultar el documento. | C7: Legal
A8: categoria | B8: Macroclasificación del contenido. | C8: Gestión Documental
A9: estado | B9: Estado documental o de atención. | C9: Vigente
A10: nivel_confidencialidad | B10: Nivel de acceso o sensibilidad. | C10: Interno
A11: prioridad | B11: Prioridad de revisión o atención. | C11: Alta
A12: texto_documento | B12: Contenido completo extraído del documento. Es el campo principal para embeddings y búsqueda semántica. | C12: Texto completo...
... A18: observaciones | B18: Notas de control o calidad del registro. | C18: Registro inicial

Sheet Resumen
A1: Resumen del Dataset Documental
A3: Métrica | B3: Valor | F3: Categoría | G3: Cantidad | I3: Tipo documento | J3: Cantidad
A4: Total documentos | B4: =COUNTA(Dataset_Documentos!A2:A201) | F4: Legal | G4: =COUNTIF(Dataset_Documentos!G2:G201,"Legal") | I4: Contrato | J4: =COUNTIF(Dataset_Documentos!B2:B201,"Contrato")
A5: Documentos vigentes | B5: =COUNTIF(Dataset_Documentos!H2:H201,"Vigente") | F5: Comercial | G5: =COUNTIF(Dataset_Documentos!G2:G201,"Comercial") | I5: Oficio | J5: =COUNTIF(Dataset_Documentos!B2:B201,"Oficio")
A6: Documentos pendientes | B6: =COUNTIF(Dataset_Documentos!H2:H201,"Pendiente") | F6: Técnico | G6: =COUNTIF(Dataset_Documentos!G2:G201,"Técnico") | I6: Informe Técnico | J6: =COUNTIF(Dataset_Documentos!B2:B201,"Informe Técnico")
A7: Documentos críticos | B7: =COUNTIF(Dataset_Documentos!J2:J201,"Crítica") | F7: Administrativo | G7: =COUNTIF(Dataset_Documentos!G2:G201,"Administrativo") | I7: Carta | J7: =COUNTIF(Dataset_Documentos!B2:B201,"Carta")
A8: Campo principal para IA | B8: texto_documento | F8: Operaciones | G8: =COUNTIF(Dataset_Documentos!G2:G201,"Operaciones") | I8: Acta | J8: =COUNTIF(Dataset_Documentos!B2:B201,"Acta")
F9: Financiero | G9: =COUNTIF(Dataset_Documentos!G2:G201,"Financiero") | I9: Resolución | J9: =COUNTIF(Dataset_Documentos!B2:B201,"Resolución")
F10: Soporte | G10: =COUNTIF(Dataset_Documentos!G2:G201,"Soporte") | I10: Solicitud | J10: =COUNTIF(Dataset_Documentos!B2:B201,"Solicitud")
F11: Gestión Documental | G11: =COUNTIF(Dataset_Documentos!G2:G201,"Gestión Documental") | I11: Memorando | J11: =COUNTIF(Dataset_Documentos!B2:B201,"Memorando")
I12: Expediente | J12: =COUNTIF(Dataset_Documentos!B2:B201,"Expediente")
I13: Reclamo | J13: =COUNTIF(Dataset_Documentos!B2:B201,"Reclamo")
